anise/__init__.py
anise/__init__.pyi
anise/_anise.cpython-314-i386-linux-gnu.so
anise/analysis.py
anise/analysis.pyi
anise/astro.py
anise/astro.pyi
anise/constants.py
anise/constants.pyi
anise/instrument/__init__.py
anise/instrument/__init__.pyi
anise/py.typed
anise/rotation.py
anise/rotation.pyi
anise/time.py
anise/time.pyi
anise/utils.py
anise/utils.pyi
anise-0.9.1.dist-info/METADATA
anise-0.9.1.dist-info/WHEEL
anise-0.9.1.dist-info/entry_points.txt
anise-0.9.1.dist-info/RECORD
