Metadata-Version: 2.4
Name: anise
Version: 0.9.1
Classifier: Programming Language :: Rust
Classifier: Programming Language :: Python :: Implementation :: CPython
Classifier: Programming Language :: Python :: Implementation :: PyPy
Summary: ANISE provides a toolkit and files for Attitude, Navigation, Instrument, Spacecraft, and Ephemeris data. It's a modern replacement of NAIF SPICE file.
Home-Page: https://nyxspace.com/
Author: Christopher Rabotin <christopher.rabotin@gmail.com>
Author-email: Christopher Rabotin <christopher.rabotin@gmail.com>
License: MPL-2.0
Requires-Python: >=3.9
Project-URL: Homepage, https://nyxspace.com/
Project-URL: Source Code, https://github.com/nyx-space/anise
